doteval_datasets/__init__.py
doteval_datasets/bfcl.py
doteval_datasets/gsm8k.py
doteval_datasets/sroie.py
dottxt_eval_datasets-0.1.0.dist-info/METADATA
dottxt_eval_datasets-0.1.0.dist-info/WHEEL
dottxt_eval_datasets-0.1.0.dist-info/entry_points.txt
dottxt_eval_datasets-0.1.0.dist-info/top_level.txt
dottxt_eval_datasets-0.1.0.dist-info/RECORD
