Metadata-Version: 2.4
Name: dottxt-eval-datasets
Version: 0.1.0
Summary: Standard datasets for doteval LLM evaluations
Author: .txt
Project-URL: repository, https://github.com/dottxt-ai/doteval-datasets
Requires-Python: >=3.10
Requires-Dist: dottxt-eval
Requires-Dist: datasets
Requires-Dist: Pillow
Provides-Extra: test
Requires-Dist: pytest; extra == "test"
Requires-Dist: pytest-asyncio; extra == "test"
